decrypt_cookies-0.1.6.dist-info/METADATA
decrypt_cookies-0.1.6.dist-info/WHEEL
decrypt_cookies.libs/libgcc_s-98a1ef30.so.1
decrypt_cookies/__init__.py
decrypt_cookies/decrypt_cookies.cpython-313-x86_64-linux-musl.so
decrypt_cookies/decrypt_cookies.pyi
decrypt_cookies/py.typed
decrypt_cookies-0.1.6.dist-info/RECORD
