Metadata-Version: 2.4
Name: decrypt_cookies
Version: 0.1.6
Classifier: Programming Language :: Python :: Implementation :: CPython
Classifier: Programming Language :: Python :: Implementation :: PyPy
Classifier: Programming Language :: Rust
Classifier: Topic :: Internet :: WWW/HTTP
Classifier: Topic :: Internet :: WWW/HTTP :: Browsers
Classifier: Topic :: Internet :: WWW/HTTP :: Session
Requires-Dist: requests>=2.23.0,<3.0.0 ; extra == 'requests'
Provides-Extra: requests
Summary: Decrypt cookies from browser
Keywords: Chromium,Firefox,Safari,cookies,decrypt
Home-Page: https://github.com/saying121/tidy-browser/tree/master/bindgen/python
Author-email: saying121 <sayin121@outlook.com>
License-Expression: LGPL-3.0-or-later
Requires-Python: >=3.8
Project-URL: homepage, https://github.com/saying121/tidy-browser/tree/master/bindgen/python
Project-URL: repository, https://github.com/saying121/tidy-browser
